edge_playback/__init__.py
edge_playback/__main__.py
edge_playback/py.typed
edge_playback/util.py
edge_playback/win32_playback.py
edge_tts/__init__.py
edge_tts/__main__.py
edge_tts/communicate.py
edge_tts/constants.py
edge_tts/data_classes.py
edge_tts/drm.py
edge_tts/exceptions.py
edge_tts/py.typed
edge_tts/srt_composer.py
edge_tts/submaker.py
edge_tts/typing.py
edge_tts/util.py
edge_tts/version.py
edge_tts/voices.py
edge_tts-7.2.6.dist-info/licenses/LICENSE
edge_tts-7.2.6.dist-info/METADATA
edge_tts-7.2.6.dist-info/WHEEL
edge_tts-7.2.6.dist-info/entry_points.txt
edge_tts-7.2.6.dist-info/top_level.txt
edge_tts-7.2.6.dist-info/RECORD
