Metadata-Version: 2.4
Name: edge-tts
Version: 7.2.6
Summary: Microsoft Edge's TTS
Home-page: https://github.com/rany2/edge-tts
Author: rany
Author-email: ranygh@riseup.net
Project-URL: Bug Tracker, https://github.com/rany2/edge-tts/issues
Classifier: Programming Language :: Python :: 3
Classifier: License :: OSI Approved :: GNU Lesser General Public License v3 (LGPLv3)
Classifier: Operating System :: OS Independent
Requires-Python: >=3.7
License-File: LICENSE
Requires-Dist: aiohttp<4.0.0,>=3.8.0
Requires-Dist: certifi>=2023.11.17
Requires-Dist: tabulate<1.0.0,>=0.4.4
Requires-Dist: typing-extensions<5.0.0,>=4.1.0
Provides-Extra: dev
Requires-Dist: black; extra == "dev"
Requires-Dist: isort; extra == "dev"
Requires-Dist: mypy; extra == "dev"
Requires-Dist: pylint; extra == "dev"
Requires-Dist: types-tabulate; extra == "dev"
Dynamic: license-file
Dynamic: requires-dist
